[
  {
    "name": "タウンライフエクステリア",
    "slug": "townlife-exterior",
    "tagline": "最大5社から無料一括見積もり",
    "description": "タウンライフエクステリアは、全国の優良外構業者に一括で見積もり依頼ができるサービスです。厳選された加盟業者のみに依頼できるため、安心して比較検討できます。",
    "features": ["最大5社無料一括見積もり", "厳選加盟業者のみ", "外構専門サービス", "プラン提案あり", "全国対応"],
    "pros": ["外構専門なので提案の質が高い", "業者の審査基準が厳しい", "比較しやすいプラン提案書あり"],
    "cons": ["対応エリアが一部制限あり", "見積もりまで数日かかる場合あり"],
    "avgCost": "80〜300万円",
    "coverage": "全国",
    "officialUrl": "https://www.town-life.jp/exterior/"
  },
  {
    "name": "ガーデンプラス",
    "slug": "garden-plus",
    "tagline": "庭・外構工事のプロ集団",
    "description": "ガーデンプラスは、庭づくりと外構工事の専門会社です。デザインから施工まで一貫して対応し、豊富な施工実績を持ちます。",
    "features": ["デザインから施工まで一貫対応", "豊富な施工実績", "保証制度あり", "アフターサポート充実", "無料相談可"],
    "pros": ["施工品質が高い", "デザイン提案力が優秀", "アフターフォローが丁寧"],
    "cons": ["価格帯がやや高め", "地域によって担当者の差あり"],
    "avgCost": "100〜400万円",
    "coverage": "全国主要都市",
    "officialUrl": "https://www.garden-plus.jp/"
  },
  {
    "name": "エクスショップ",
    "slug": "ex-shop",
    "tagline": "外構工事最安値挑戦中",
    "description": "エクスショップは、外構商品の販売と施工を手がけるインターネット通販型の外構業者です。商品を自社で仕入れることで低コストを実現しています。",
    "features": ["ネット通販型で低コスト", "商品ラインナップ豊富", "無料見積もり対応", "DIY向け商品も充実", "カーポート・フェンス得意"],
    "pros": ["価格が業界最安値水準", "商品選択の自由度が高い", "施工実績が豊富"],
    "cons": ["施工は外注業者の場合あり", "細かいデザイン提案は弱め"],
    "avgCost": "30〜200万円",
    "coverage": "全国",
    "officialUrl": "https://www.ex-shop.co.jp/"
  },
  {
    "name": "リショップナビ",
    "slug": "rishop-navi",
    "tagline": "最大5社から見積もり比較",
    "description": "リショップナビは、リフォーム全般に強い見積もり比較サービスです。外構・庭工事も対応しており、厳選業者への一括見積もりが可能です。",
    "features": ["最大5社無料一括見積もり", "リフォーム全般対応", "厳選業者のみ紹介", "相談サポート充実", "口コミ確認可能"],
    "pros": ["リフォーム全般と組み合わせて相談できる", "業者の口コミが豊富", "コーディネーターのサポートあり"],
    "cons": ["外構専門サービスより提案力が弱い場合あり", "業者数が地域によって異なる"],
    "avgCost": "50〜300万円",
    "coverage": "全国",
    "officialUrl": "https://rishop.co.jp/"
  },
  {
    "name": "ホームプロ",
    "slug": "home-pro",
    "tagline": "リフォーム会社比較の王道",
    "description": "ホームプロは、日本最大級のリフォーム会社比較サイトです。外構・庭工事を含む様々なリフォームで業者比較ができます。",
    "features": ["日本最大級の加盟業者数", "口コミ・評価が充実", "無料一括見積もり", "施工事例多数掲載", "相談員サポートあり"],
    "pros": ["加盟業者数が圧倒的に多い", "口コミが豊富で参考になる", "サービスの信頼性が高い"],
    "cons": ["業者の質にばらつきがある場合あり", "外構専門ではないため提案に差あり"],
    "avgCost": "50〜500万円",
    "coverage": "全国",
    "officialUrl": "https://www.homepro.co.jp/"
  },
  {
    "name": "くらしのマーケット",
    "slug": "kurashi-no-market",
    "tagline": "口コミで選ぶ地元の職人",
    "description": "くらしのマーケットは、家事・修理・外構など様々なサービスを提供するプロを口コミで探して予約できるプラットフォームです。",
    "features": ["口コミ評価で選べる", "価格の透明性が高い", "オンライン予約可能", "小規模工事得意", "地元業者が多い"],
    "pros": ["口コミが豊富で選びやすい", "小規模工事から対応可能", "価格が明確"],
    "cons": ["大規模工事には不向きな場合あり", "業者の専門性にばらつきあり"],
    "avgCost": "5〜100万円",
    "coverage": "全国主要都市",
    "officialUrl": "https://curama.jp/"
  },
  {
    "name": "ミツモア",
    "slug": "mitsumoa",
    "tagline": "かんたん3分で見積もり依頼",
    "description": "ミツモアは、様々なサービスのプロにかんたんに見積もり依頼ができるプラットフォームです。外構工事も対応しています。",
    "features": ["3分で見積もり依頼完了", "複数業者から提案", "チャットで相談可能", "小〜中規模工事対応", "無料見積もり"],
    "pros": ["見積もり依頼が簡単", "複数の提案を比較できる", "チャットで気軽に相談できる"],
    "cons": ["大規模工事には専門サービスがおすすめ", "業者の専門性にばらつきあり"],
    "avgCost": "10〜150万円",
    "coverage": "全国",
    "officialUrl": "https://meetsmore.com/"
  },
  {
    "name": "比較ビズ",
    "slug": "hikaku-biz",
    "tagline": "法人・個人どちらも対応",
    "description": "比較ビズは、外構工事を含む様々なサービスを一括比較できるプラットフォームです。法人・個人どちらの依頼にも対応しています。",
    "features": ["法人・個人両対応", "一括見積もり対応", "様々なサービスに対応", "無料相談可能", "業者の実績確認可"],
    "pros": ["法人案件にも対応できる", "幅広いサービスに対応", "見積もり比較がしやすい"],
    "cons": ["外構専門ではないため専門性が低い場合あり", "業者数が他サービスより少ない"],
    "avgCost": "50〜300万円",
    "coverage": "全国",
    "officialUrl": "https://www.hikakubiz.net/"
  },
  {
    "name": "外構パートナーズ",
    "slug": "gaiko-partners",
    "tagline": "外構専門の信頼できる業者紹介",
    "description": "外構パートナーズは、外構工事専門の業者紹介サービスです。厳選された外構業者のみに依頼でき、高品質な施工が期待できます。",
    "features": ["外構専門業者のみ紹介", "厳選審査済み業者", "無料一括見積もり", "施工保証あり", "全国対応"],
    "pros": ["外構専門なので提案の質が高い", "業者審査が厳しく安心", "施工保証があるため安心"],
    "cons": ["知名度がやや低い", "登録業者数が他サービスより少ない"],
    "avgCost": "60〜300万円",
    "coverage": "全国",
    "officialUrl": "https://gaiko-partners.com/"
  },
  {
    "name": "リフォームガイド",
    "slug": "reform-guide",
    "tagline": "リフォームの総合ガイド",
    "description": "リフォームガイドは、リフォーム全般の情報提供と業者紹介を行うサービスです。外構・庭工事の業者紹介にも対応しています。",
    "features": ["リフォーム情報が豊富", "業者紹介対応", "無料相談可能", "コラム・事例が充実", "費用相場情報あり"],
    "pros": ["リフォーム情報が豊富で参考になる", "費用相場が明確", "コンテンツが充実している"],
    "cons": ["業者紹介機能は他サービスに劣る", "外構専門ではない"],
    "avgCost": "50〜400万円",
    "coverage": "全国",
    "officialUrl": "https://reform-guide.com/"
  }
]
